pytop/__init__.py
pytop/monitor.py
PyTop_B-1.0.0.dist-info/LICENSE
PyTop_B-1.0.0.dist-info/METADATA
PyTop_B-1.0.0.dist-info/WHEEL
PyTop_B-1.0.0.dist-info/entry_points.txt
PyTop_B-1.0.0.dist-info/top_level.txt
PyTop_B-1.0.0.dist-info/RECORD
